{
    "pools": [
        {
            "rolls": 1,
            "entries": [
                {
                    "type": "minecraft:item",
                    "name": "minecraft:rotten_flesh",
                    "functions": [
                        {
                            "function": "minecraft:set_count",
                            "count": {
                                "min": 80,
                                "max": 120
                            }
                        }
                    ]
                }
            ]
        },
        {
            "rolls": {
                "min": 1,
                "max": 2
            },
            "entries": [
                {
                    "type": "minecraft:item",
                    "name": "minecraft:carrot",
                    "functions": [
                        {
                            "function": "minecraft:set_count",
                            "count": {
                                "min": 3,
                                "max": 7
                            }
                        }
                    ]
                },
                {
                    "type": "minecraft:item",
                    "name": "minecraft:potato",
                    "functions": [
                        {
                            "function": "minecraft:set_count",
                            "count": {
                                "min": 3,
                                "max": 7
                            }
                        }
                    ]
                }
            ]
        },
        {
            "rolls": 1,
            "entries": [
                {
                    "type": "minecraft:loot_table",
                    "name": "dnl:structures/dungeon/chests/materials/common",
                    "functions": [
                        {
                            "function": "minecraft:set_count",
                            "count": 2
                        }
                    ]
                }
            ]
        }
    ]
}